xpresslibs/__init__.py
xpresslibs/lib/xknitro.dll
xpresslibs/lib/xpnll.dll
xpresslibs/lib/xprl.dll
xpresslibs/lib/xprs.dll
xpresslibs/lib/xprscuda.dll
xpresslibs/lib/xprsws.dll
xpresslibs/lib/xpressdeps/jansson.dll
xpresslibs/lib/xpressdeps/libcrypto-3-x64.dll
xpresslibs/lib/xpressdeps/libcurl.dll
xpresslibs/lib/xpressdeps/libiomp5md.dll
xpresslibs/lib/xpressdeps/libssl-3-x64.dll
xpresslibs/lib/xpressdeps/libzip.dll
xpresslibs/lib/xpressdeps/websockets.dll
xpresslibs-9.8.0.dist-info/licenses/LICENSE.txt
xpresslibs-9.8.0.dist-info/METADATA
xpresslibs-9.8.0.dist-info/WHEEL
xpresslibs-9.8.0.dist-info/top_level.txt
xpresslibs-9.8.0.dist-info/RECORD
