Metadata-Version: 2.4
Name: xpresslibs
Version: 9.8.0
Summary: FICO Xpress Optimizer solver libraries
Home-page: https://www.fico.com/en/products/fico-xpress-optimization
Author: FICO Xpress Optimizer dev. team
Author-email: support@fico.com
Keywords: optimization mip minlp xpress
Platform: any
Classifier: Development Status :: 5 - Production/Stable
Classifier: Intended Audience :: Science/Research
Classifier: Intended Audience :: Developers
Classifier: Programming Language :: C
Classifier: Programming Language :: C++
Classifier: Topic :: Software Development
Classifier: Topic :: Scientific/Engineering
Classifier: Operating System :: Microsoft :: Windows
Classifier: Operating System :: POSIX :: Linux
Classifier: Operating System :: MacOS
Classifier: License :: Other/Proprietary License
License-File: LICENSE.txt
Dynamic: author
Dynamic: author-email
Dynamic: classifier
Dynamic: description
Dynamic: description-content-type
Dynamic: home-page
Dynamic: keywords
Dynamic: license-file
Dynamic: platform
Dynamic: summary
